hathitrust_api/__init__.py
hathitrust_api/bib_api.py
hathitrust_api/constants.py
hathitrust_api/data_api.py
hathitrust_api/solr_api.py
hathitrust_api-0.1.1.dist-info/METADATA
hathitrust_api-0.1.1.dist-info/RECORD
hathitrust_api-0.1.1.dist-info/WHEEL
hathitrust_api-0.1.1.dist-info/top_level.txt
