Metadata-Version: 2.1
Name: hathitrust-api
Version: 0.1.1
Summary: Python wrappers for the HathiTrust APIs
Home-page: https://github.com/rlmv/hathitrust-api
Author: Bo Marchman
Author-email: bo.marchman@gmail.com
License: MIT
Platform: UNKNOWN
Classifier: Programming Language :: Python :: 2
Classifier: Programming Language :: Python :: 3
Classifier: License :: OSI Approved :: MIT License
Requires-Dist: requests
Requires-Dist: requests-oauthlib
